Classfile /F:/SyFinal/_mine/JavaLadder/src/com/sunladder/test/classload/ploy/TestPoly$Child.class
  Last modified 2018-7-17; size 564 bytes
  MD5 checksum 3c1b72e671dc76a7dc1bad803e83a4e5
  Compiled from "TestPoly.java"
class com.sunladder.test.classload.ploy.TestPoly$Child extends com.sunladder.test.classload.ploy.TestPoly$Parent
  minor version: 0
  major version: 52
  flags: ACC_SUPER
Constant pool:
   #1 = Methodref          #6.#14         // com/sunladder/test/classload/ploy/TestPoly$Parent."<init>":()V
   #2 = Fieldref           #15.#16        // java/lang/System.out:Ljava/io/PrintStream;
   #3 = String             #17            // Child
   #4 = Methodref          #18.#19        // java/io/PrintStream.println:(Ljava/lang/String;)V
   #5 = Class              #21            // com/sunladder/test/classload/ploy/TestPoly$Child
   #6 = Class              #23            // com/sunladder/test/classload/ploy/TestPoly$Parent
   #7 = Utf8               <init>
   #8 = Utf8               ()V
   #9 = Utf8               Code
  #10 = Utf8               LineNumberTable
  #11 = Utf8               print
  #12 = Utf8               SourceFile
  #13 = Utf8               TestPoly.java
  #14 = NameAndType        #7:#8          // "<init>":()V
  #15 = Class              #25            // java/lang/System
  #16 = NameAndType        #26:#27        // out:Ljava/io/PrintStream;
  #17 = Utf8               Child
  #18 = Class              #28            // java/io/PrintStream
  #19 = NameAndType        #29:#30        // println:(Ljava/lang/String;)V
  #20 = Class              #31            // com/sunladder/test/classload/ploy/TestPoly
  #21 = Utf8               com/sunladder/test/classload/ploy/TestPoly$Child
  #22 = Utf8               InnerClasses
  #23 = Utf8               com/sunladder/test/classload/ploy/TestPoly$Parent
  #24 = Utf8               Parent
  #25 = Utf8               java/lang/System
  #26 = Utf8               out
  #27 = Utf8               Ljava/io/PrintStream;
  #28 = Utf8               java/io/PrintStream
  #29 = Utf8               println
  #30 = Utf8               (Ljava/lang/String;)V
  #31 = Utf8               com/sunladder/test/classload/ploy/TestPoly
{
  public com.sunladder.test.classload.ploy.TestPoly$Child();
    descriptor: ()V
    flags: ACC_PUBLIC
    Code:
      stack=1, locals=1, args_size=1
         0: aload_0
         1: invokespecial #1                  // Method com/sunladder/test/classload/ploy/TestPoly$Parent."<init>":()V
         4: return
      LineNumberTable:
        line 19: 0
        line 21: 4

  void print();
    descriptor: ()V
    flags:
    Code:
      stack=2, locals=1, args_size=1
         0: getstatic     #2                  // Field java/lang/System.out:Ljava/io/PrintStream;
         3: ldc           #3                  // String Child
         5: invokevirtual #4                  // Method java/io/PrintStream.println:(Ljava/lang/String;)V
         8: return
      LineNumberTable:
        line 25: 0
        line 26: 8
}
SourceFile: "TestPoly.java"
InnerClasses:
     static #17= #5 of #20; //Child=class com/sunladder/test/classload/ploy/TestPoly$Child of class com/sunladder/test/classload/ploy/TestPoly
     static #24= #6 of #20; //Parent=class com/sunladder/test/classload/ploy/TestPoly$Parent of class com/sunladder/test/classload/ploy/TestPoly
