Classfile /D:/ASWorkSpace/_mine/JavaLadder/src/com/sunladder/test/classload/block/TestStaticBlock$Test3.class
  Last modified 2018-7-16; size 444 bytes
  MD5 checksum 777b881823c7681ec125c2876874d6c7
  Compiled from "TestStaticBlock.java"
class com.sunladder.test.classload.block.TestStaticBlock$Test3
  minor version: 0
  major version: 52
  flags: ACC_SUPER
Constant pool:
   #1 = Methodref          #4.#14         // java/lang/Object."<init>":()V
   #2 = Fieldref           #3.#15         // com/sunladder/test/classload/block/TestStaticBlock$Test3.value:I
   #3 = Class              #17            // com/sunladder/test/classload/block/TestStaticBlock$Test3
   #4 = Class              #20            // java/lang/Object
   #5 = Utf8               value
   #6 = Utf8               I
   #7 = Utf8               <init>
   #8 = Utf8               ()V
   #9 = Utf8               Code
  #10 = Utf8               LineNumberTable
  #11 = Utf8               <clinit>
  #12 = Utf8               SourceFile
  #13 = Utf8               TestStaticBlock.java
  #14 = NameAndType        #7:#8          // "<init>":()V
  #15 = NameAndType        #5:#6          // value:I
  #16 = Class              #21            // com/sunladder/test/classload/block/TestStaticBlock
  #17 = Utf8               com/sunladder/test/classload/block/TestStaticBlock$Test3
  #18 = Utf8               Test3
  #19 = Utf8               InnerClasses
  #20 = Utf8               java/lang/Object
  #21 = Utf8               com/sunladder/test/classload/block/TestStaticBlock
{
  public static int value;
    descriptor: I
    flags: ACC_PUBLIC, ACC_STATIC

  com.sunladder.test.classload.block.TestStaticBlock$Test3();
    descriptor: ()V
    flags:
    Code:
      stack=1, locals=1, args_size=1
         0: aload_0
         1: invokespecial #1                  // Method java/lang/Object."<init>":()V
         4: return
      LineNumberTable:
        line 24: 0

  static {};
    descriptor: ()V
    flags: ACC_STATIC
    Code:
      stack=1, locals=0, args_size=0
         0: iconst_2
         1: putstatic     #2                  // Field value:I
         4: iconst_1
         5: putstatic     #2                  // Field value:I
         8: iconst_3
         9: putstatic     #2                  // Field value:I
        12: return
      LineNumberTable:
        line 27: 0
        line 30: 4
        line 33: 8
        line 34: 12
}
SourceFile: "TestStaticBlock.java"
InnerClasses:
     static #18= #3 of #16; //Test3=class com/sunladder/test/classload/block/TestStaticBlock$Test3 of class com/sunladder/test/classload/block/TestStaticBlock
